CHANGELOG.rst
CONTRIBUTORS.rst
MANIFEST.in
README.rst
VERSION.txt
setup.cfg
setup.py
Flask_HAL.egg-info/PKG-INFO
Flask_HAL.egg-info/SOURCES.txt
Flask_HAL.egg-info/dependency_links.txt
Flask_HAL.egg-info/requires.txt
Flask_HAL.egg-info/top_level.txt
flask_hal/__init__.py
flask_hal/document.py
flask_hal/link.py