Metadata-Version: 1.1
Name: Flask-HAL
Version: 1.0.4
Summary: Provides easy integration of the HAL specification for your REST Flask Applications.
Home-page: https://github.com/thisissoon/Flask-HAL
Author: SOON_
Author-email: dorks@thisissoon.com
License: Public Domain
Keywords: Flask,HAL,REST,Views
Platform: UNKNOWN
Classifier: Framework :: Flask
Classifier: Environment :: Web Environment
Classifier: Intended Audience :: Developers
Classifier: License :: OSI Approved :: MIT License
Classifier: Development Status :: 5 - Production/Stable
Classifier: Operating System :: OS Independent
Classifier: Programming Language :: Python
Classifier: Programming Language :: Python :: 2.7
Classifier: Programming Language :: Python :: 3
Classifier: Programming Language :: Python :: 3.3
Classifier: Programming Language :: Python :: 3.4
Classifier: Topic :: Software Development
Classifier: Topic :: Software Development :: Libraries :: Python Modules
Classifier: Topic :: Internet :: WWW/HTTP :: Dynamic Content
Classifier: License :: Public Domain
